breads/__init__.py
breads/calibration.py
breads/search_planet.py
breads/utils.py
breads/instruments/OSIRIS.py
breads/instruments/__init__.py
breads/instruments/instrument.py
breads-0.0.1.dist-info/METADATA
breads-0.0.1.dist-info/WHEEL
breads-0.0.1.dist-info/top_level.txt
breads-0.0.1.dist-info/RECORD
